{
	"configurations" : 
	[
		{
			"directories" : 
			[
				{
					"build" : ".",
					"childIndexes" : 
					[
						1,
						2,
						3
					],
					"jsonFile" : "directory-.-Debug-d0094a50bb2071803777.json",
					"minimumCMakeVersion" : 
					{
						"string" : "3.1"
					},
					"projectIndex" : 0,
					"source" : "."
				},
				{
					"build" : "traffic_light",
					"jsonFile" : "directory-traffic_light-Debug-a2a9bdf7dded54189db1.json",
					"minimumCMakeVersion" : 
					{
						"string" : "3.9"
					},
					"parentIndex" : 0,
					"projectIndex" : 1,
					"source" : "traffic_light",
					"targetIndexes" : 
					[
						1
					]
				},
				{
					"build" : "Header",
					"jsonFile" : "directory-Header-Debug-52fd1039c5f97a366cea.json",
					"minimumCMakeVersion" : 
					{
						"string" : "3.9"
					},
					"parentIndex" : 0,
					"projectIndex" : 0,
					"source" : "Header"
				},
				{
					"build" : "cars",
					"jsonFile" : "directory-cars-Debug-d0191f7e16938e74dfc6.json",
					"minimumCMakeVersion" : 
					{
						"string" : "3.9"
					},
					"parentIndex" : 0,
					"projectIndex" : 0,
					"source" : "cars",
					"targetIndexes" : 
					[
						0
					]
				}
			],
			"name" : "Debug",
			"projects" : 
			[
				{
					"childIndexes" : 
					[
						1
					],
					"directoryIndexes" : 
					[
						0,
						2,
						3
					],
					"name" : "ProjetsCIR2",
					"targetIndexes" : 
					[
						0
					]
				},
				{
					"directoryIndexes" : 
					[
						1
					],
					"name" : "thread_example",
					"parentIndex" : 0,
					"targetIndexes" : 
					[
						1
					]
				}
			],
			"targets" : 
			[
				{
					"directoryIndex" : 3,
					"id" : "Cars::@5ab15ec482437d72f95f",
					"jsonFile" : "target-Cars-Debug-469f4d58707af86be04e.json",
					"name" : "Cars",
					"projectIndex" : 0
				},
				{
					"directoryIndex" : 1,
					"id" : "traffic_light::@121fe675099b3038c5ed",
					"jsonFile" : "target-traffic_light-Debug-e67003b33a22f4c268c6.json",
					"name" : "traffic_light",
					"projectIndex" : 1
				}
			]
		}
	],
	"kind" : "codemodel",
	"paths" : 
	{
		"build" : "C:/Users/titouan.gouello/source/repos/ProjetsCIR2_Transports/out/build/x64-Debug",
		"source" : "C:/Users/titouan.gouello/source/repos/ProjetsCIR2_Transports"
	},
	"version" : 
	{
		"major" : 2,
		"minor" : 6
	}
}
